{
  "name": "Naropa",
  "slug": "naropa",
  "bio": "Naropa (1016–1100) was an Indian Buddhist scholar and mahasiddha who left his position as abbot of Nalanda University to seek his teacher Tilopa. After years of arduous trials, he received the complete Mahamudra transmission and developed the Six Yogas of Naropa, a set of advanced tantric practices. He transmitted these teachings to Marpa the Translator, who carried them to Tibet.",
  "photo": "/images/teachers/naropa.jpg",
  "website": null,
  "birth_year": 1016,
  "death_year": 1100,
  "city": "Nalanda",
  "state": "Bihar",
  "country": "IN",
  "latitude": 25.1364914,
  "longitude": 85.4436546,
  "traditions": [
    "vajrayana"
  ],
  "centers": []
}
