{
  "title": "The Life of St. Teresa of Jesus",
  "slug": "avila-the-life-of-st-teresa-of-jesus",
  "type": "book",
  "category": "popular",
  "url": "https://bookshop.org/a/LINEAGE/9781521170700",
  "author": "St. Teresa of Avila",
  "year": 2017,
  "description": "How is this book unique? Font adjustments & biography included Unabridged (100% Original content) Illustrated About The Life of St. Teresa of Jesus by St. Teresa Of Avila \"In this landmark of Christian mysticism, the revered Carmelite nun presents moving accounts of her profound religious experience",
  "traditions": [
    "christian-mysticism"
  ],
  "teachers": [
    "st-teresa-of-avila"
  ],
  "centers": []
}
