{
  "title": "The Yoga Sutras Of Patanjali - The Book Of The Spiritual Man (Annotated Edition)",
  "slug": "patanjali-the-yoga-sutras-of-patanjali-the-book-of-the-spiritual-man-annotated-e",
  "type": "book",
  "category": "popular",
  "url": "https://bookshop.org/a/LINEAGE/9783849619121",
  "author": "Patanjali",
  "year": 2012,
  "description": "This edition includes an extensive preface by Swami Vivekananda, the chief disciple of the 19th century mystic Ramakrishna Paramahansa and the founder of the Ramakrishna Math and the Ramakrishna Mission. He gives the reader deep insights about Yoga and the Ultimate Goal in Life. The Yoga Sutras of P",
  "traditions": [
    "classical-yoga"
  ],
  "teachers": [
    "patanjali"
  ],
  "centers": []
}
