{
  "title": "Finding Your Way",
  "slug": "salzberg-finding-your-way",
  "type": "book",
  "category": "popular",
  "url": "https://bookshop.org/a/LINEAGE/9781523526017",
  "author": "Sharon Salzberg",
  "year": 2023,
  "description": "Find a sense of calm and hope with this illustrated gift book from the world renowned and bestselling meditation teacher as she offers bite-sized tidbits of inspiring advice. Finding Your Way is the newest book from the one of the most beloved and bestselling meditation teachers. In dozens of clear and inspiring entries, readers will be reminded that there are many ways to stay calm and move forward. From choosing to simply \"do the good that is in front of you,\" to reading a meaningful piece from an interview with a kind leader, to quotes from people Sharon admires, and reminders of how to practice meditation, Finding Your Way will show readers that they are always on the right path, because it is their own. Each thought, whether a single quote or a short essay, is presented in a visually calm manner, with dozens of four color illustrations to enhance and inspire the experience throughout the book.",
  "traditions": [
    "theravada",
    "vipassana-movement"
  ],
  "teachers": [
    "sharon-salzberg"
  ],
  "centers": []
}
