{
  "title": "The Way of the Bodhisattva",
  "slug": "the-way-of-the-bodhisattva",
  "type": "book",
  "category": "primary_text",
  "url": "https://bookshop.org/a/122188/9781590303887",
  "author": "Shantideva",
  "year": 700,
  "description": "A guide to cultivating the mind of enlightenment through love, compassion, generosity, and patience, studied in an unbroken tradition for centuries.",
  "traditions": [
    "mahayana",
    "tibetan-buddhism-kagyu",
    "tibetan-buddhism-nyingma",
    "tibetan-buddhism-gelug"
  ],
  "teachers": [],
  "centers": []
}
