{
  "title": "The Citadel of Awareness",
  "slug": "thubten-the-citadel-of-awareness",
  "type": "book",
  "category": "popular",
  "url": "https://bookshop.org/a/LINEAGE/9781732020849",
  "author": "Anam Thubten",
  "year": 2021,
  "description": "The Dzogchen Aspiration Prayer by eighteenth-century Dzogchen master, Jigme Lingpa, thoroughly covers the entire system of Dzogchen. This book is a commentary on that prayer, one of the most revered texts in the Nyingma Buddhist tradition.",
  "traditions": [
    "dzogchen",
    "tibetan-buddhism-gelug",
    "vajrayana"
  ],
  "teachers": [
    "anam-thubten"
  ],
  "centers": []
}
