{
  "title": "Seasons of the Sacred",
  "slug": "vaughan-lee-seasons-of-the-sacred",
  "type": "book",
  "category": "popular",
  "url": "https://bookshop.org/a/LINEAGE/9781941394465",
  "author": "Llewellyn Vaughan-Lee",
  "year": 2021,
  "description": "Seasons of the Sacred weaves together poems, images, and stories of Spring, Summer, Autumn, and Winter, reconnecting us to our roots in the cycles of nature and our own soul. As our world appears more and more out of balance, our destruction of the natural world increasing, there is a vital need to",
  "traditions": [
    "sufism"
  ],
  "teachers": [
    "llewellyn-vaughan-lee"
  ],
  "centers": []
}
