{
  "title": "Dudjom Rinpoche — Wisdom of the Masters",
  "slug": "wisdom-masters-dudjom-rinpoche",
  "type": "video",
  "category": "web_resource",
  "url": "https://www.youtube.com/@SamaneriJayasara/search?query=Dudjom+Rinpoche",
  "author": "Samaneri Jayasāra",
  "year": null,
  "description": "Audio teachings and readings from Dudjom Rinpoche, curated by Samaneri Jayasāra on the Wisdom of the Masters channel.",
  "traditions": [
    "vajrayana",
    "dzogchen"
  ],
  "teachers": [
    "dudjom-rinpoche"
  ],
  "centers": []
}
